crio_vault/__init__.py
crio_vault/vault.py
crio_vault-1.1.5.dist-info/METADATA
crio_vault-1.1.5.dist-info/WHEEL
crio_vault-1.1.5.dist-info/top_level.txt
crio_vault-1.1.5.dist-info/RECORD
