Metadata-Version: 2.1
Name: crio-vault
Version: 1.1.5
Summary: Vault library
Home-page: UNKNOWN
Author: Crio_Developer
License: UNKNOWN
Platform: UNKNOWN
Classifier: Intended Audience :: Developers
Classifier: License :: OSI Approved :: MIT License
Classifier: Programming Language :: Python
Classifier: Programming Language :: Python :: 3
Classifier: Programming Language :: Python :: 3.6
Classifier: Programming Language :: Python :: 3.7
Classifier: Programming Language :: Python :: 3.8
Classifier: Programming Language :: Python :: 3.9
Classifier: Operating System :: OS Independent
Requires-Dist: boto3 (==1.23.10)
Requires-Dist: botocore (==1.26.10)
Requires-Dist: requests
